Calc/Calc.py
Calc/__init__.py
calc_abce-0.0.1.dist-info/METADATA
calc_abce-0.0.1.dist-info/WHEEL
calc_abce-0.0.1.dist-info/top_level.txt
calc_abce-0.0.1.dist-info/RECORD
