Metadata-Version: 2.1
Name: calc-abce
Version: 0.0.1
Summary: test project
Requires-Python: >=3.9
Requires-Dist: numpy (>=1.23.4)
